youtube_analyzer/__init__.py
youtube_analyzer/__version__.py
youtube_analyzer/adaptive_formats.py
youtube_analyzer/api.py
youtube_analyzer/captions.py
youtube_analyzer/exeptions.py
youtube_analyzer/parsers.py
youtube_analyzer/playlists.py
youtube_analyzer/utils.py
youtube_analyzer-3.0.4.dist-info/LICENSE
youtube_analyzer-3.0.4.dist-info/METADATA
youtube_analyzer-3.0.4.dist-info/WHEEL
youtube_analyzer-3.0.4.dist-info/top_level.txt
youtube_analyzer-3.0.4.dist-info/RECORD
