Metadata-Version: 2.1
Name: youtube-analyzer
Version: 3.0.4
Summary: Analize vídeos do youtube
Author: PauloCesar-dev404
Author-email: paulocesar0073dev404@gmail.com
License: MIT
Project-URL: GitHub, https://github.com/PauloCesar-dev404/youtube_analyzer
Keywords: youtube,youtube-analyzer,analizer youtube
Platform: any
License-File: LICENSE
Requires-Dist: requests
Requires-Dist: colorama
Requires-Dist: beautifulsoup4
